{
  "source_file": "page_160.json",
  "url": [
    "https://datascience.uchicago.edu/explore-the-ms-ads-campus/"
  ],
  "canonical_url": "https://datascience.uchicago.edu/explore-the-ms-ads-campus/",
  "page_title": "Explore the MS-ADS Campus | DSI",
  "meta_description": "",
  "breadcrumbs": "Home > Explore The Ms Ads Campus",
  "scraped_at": "2026-04-19T01:43:19.605135+00:00",
  "structured_sections": [
    {
      "section_index": 2,
      "text_markdown": "## Explore the MS-ADS Campus\nWelcome to the University of Chicago’s MS in Applied Data Science program page! Take a look at our interactive map and virtual tour and discover what awaits you in the MS in Applied Data Science program at the University of Chicago. Additionally, here’s a [link](https://grad.uchicago.edu/life-at-uchicago/housing/finding-an-apartment/other-chicago-neighborhoods) to explore common neighborhoods UChicago graduate students live in. If you would like more information, [UChicagoGRAD](https://grad.uchicago.edu/life-at-uchicago/housing) is here to guide you.\nHere’s what you can expect:\nCampus Location: Our campus is strategically situated at the NBC Tower and Gleacher Center in downtown Chicago’s Streeterville neighborhood. These buildings will serve as the backdrop for your data science journey.\nData Science Institute: Located within Hyde Park campus, the DSI executes the University of Chicago’s bold, innovative vision of data science as an evolving discipline. Alongside other education programs and initiatives, the MS-ADS program enacts the DSI’s commitment to data science education as a conduit for real-world impact.\nChicago Landmarks: Beyond the classroom, discover Chicago’s renowned landmarks. Visit the Art Institute of Chicago, marvel at the Cloud Gate (The Bean) in Millennium Park, or catch a show at the historic Chicago Theatre. The city’s vibrant arts, music, and theater scene awaits you.\nUChicago Shuttle: Seamlessly navigate to and from the downtown and Hyde Park campuses using the convenient (and free) UGO shuttle service."
    },
    {
      "section_index": 3,
      "text_markdown": "## Virtual Tour\nCheck out the MS in Applied Data Science campus with our virtual tour. The tour below highlights two of our classrooms, merging cutting-edge innovation with top-tier education. Additionally, the tour includes a view of the student lounge, a space designed for relaxation and collaborative study.\nTake the virtual tour today to get a sense of what it’s like to be a student in the MS in Applied Data Science program."
    }
  ],
  "Note": ""
}